design.sv
// Code your design here

module d_ff(output Q, input D, clk, rst);
  reg Q;
  always@(posedge clk or posedge rst)
    begin
      if(rst) begin
        Q <= 1'b0;
      end else begin
        Q <= D;
      end
    end
endmodule

testbench.sv
// Code your testbench here
// or browse Examples

module test;
  wire Q;
  reg D;
  reg clk;
  reg rst;
  d_ff M_UUT(Q, D, clk, rst);
  initial
    begin
      
      $dumpfile("waveD.vcd");
      $dumpvars(0, Q, D, clk, rst);
      $monitor($time," rst=%b clk=%b D=%b  Q=%b ", rst, clk, D, Q);
      rst=1'b1;D=1'b0;clk=1'b0;
      #99 rst=1'b0;D=1'b1;
      #100 D=1'b0;
      #103 D=1'b1;
      #97 D=1'b0;
      #98 D=1'b1;
      #100 $finish;
    end
  always #100 clk=~clk;
endmodule

waveD.vcd
$date
	Thu May  7 08:14:18 2020
$end
$version
	Icarus Verilog
$end
$timescale
	1s
$end
$scope module test $end
$var wire 1 ! Q $end
$upscope $end
$scope module test $end
$var reg 1 " D $end
$upscope $end
$scope module test $end
$var reg 1 # clk $end
$upscope $end
$scope module test $end
$var reg 1 $ rst $end
$upscope $end
$enddefinitions $end
#0
$dumpvars
1$
0#
0"
0!
$end
#99
1"
0$
#100
1!
1#
#199
0"
#200
0#
#300
0!
1#
#302
1"
#399
0"
#400
0#
#497
1"
#500
1!
1#
